odoo/addons/purchase_container/README.rst
odoo/addons/purchase_container/__init__.py
odoo/addons/purchase_container/__manifest__.py
odoo/addons/purchase_container/data/container.type.csv
odoo/addons/purchase_container/data/cron_data.xml
odoo/addons/purchase_container/i18n/it.po
odoo/addons/purchase_container/i18n/pt_BR.po
odoo/addons/purchase_container/i18n/purchase_container.pot
odoo/addons/purchase_container/models/__init__.py
odoo/addons/purchase_container/models/container_type.py
odoo/addons/purchase_container/models/purchase_container.py
odoo/addons/purchase_container/models/purchase_order.py
odoo/addons/purchase_container/models/stock_picking.py
odoo/addons/purchase_container/readme/CONTRIBUTORS.md
odoo/addons/purchase_container/readme/DESCRIPTION.md
odoo/addons/purchase_container/security/ir.model.access.csv
odoo/addons/purchase_container/static/description/icon.png
odoo/addons/purchase_container/static/description/img.png
odoo/addons/purchase_container/static/description/index.html
odoo/addons/purchase_container/tests/__init__.py
odoo/addons/purchase_container/tests/test_module.py
odoo/addons/purchase_container/views/container_type.xml
odoo/addons/purchase_container/views/purchase.xml
odoo/addons/purchase_container/views/purchase_container.xml
odoo/addons/purchase_container/views/stock_picking.xml
odoo_addon_purchase_container-18.0.1.1.0.2.dist-info/METADATA
odoo_addon_purchase_container-18.0.1.1.0.2.dist-info/WHEEL
odoo_addon_purchase_container-18.0.1.1.0.2.dist-info/top_level.txt
odoo_addon_purchase_container-18.0.1.1.0.2.dist-info/RECORD
